feast_hive/__init__.py
feast_hive/hive.py
feast_hive/hive_source.py
feast_hive/hive_type_map.py
feast_hive-0.17.0.dist-info/LICENSE
feast_hive-0.17.0.dist-info/METADATA
feast_hive-0.17.0.dist-info/WHEEL
feast_hive-0.17.0.dist-info/top_level.txt
feast_hive-0.17.0.dist-info/RECORD
