Metadata-Version: 2.1
Name: feast-hive
Version: 0.17.0
Summary: Hive support for Feast offline store
Home-page: https://github.com/baineng/feast-hive
Author: Benn Ma
Author-email: bennmsg@gmail.com
License: Apache License, Version 2.0
Project-URL: Bug Tracker, https://github.com/baineng/feast-hive/issues
Keywords: feast featurestore hive offlinestore
Platform: UNKNOWN
Classifier: License :: OSI Approved :: Apache Software License
Classifier: Programming Language :: Python
Classifier: Programming Language :: Python :: 3
Classifier: Programming Language :: Python :: 3.7
Requires-Python: >=3.7.0
License-File: LICENSE
Requires-Dist: feast (>=0.17.0)
Requires-Dist: impyla[kerberos] (>=0.15.0)
Provides-Extra: dev
Requires-Dist: flake8 ; extra == 'dev'
Requires-Dist: black (==19.10b0) ; extra == 'dev'
Requires-Dist: isort (>=5) ; extra == 'dev'
Requires-Dist: mypy (==0.790) ; extra == 'dev'
Requires-Dist: pytest (==6.0.0) ; extra == 'dev'
Requires-Dist: pytest-xdist ; extra == 'dev'
Requires-Dist: assertpy (==1.1) ; extra == 'dev'
Provides-Extra: test
Requires-Dist: pytest (==6.0.0) ; extra == 'test'
Requires-Dist: pytest-xdist ; extra == 'test'
Requires-Dist: assertpy (==1.1) ; extra == 'test'
